card_component/__init__.py
card_component/frontend/build/asset-manifest.json
card_component/frontend/build/bootstrap.min.css
card_component/frontend/build/index.html
card_component/frontend/build/images/2nd-battery.svg
card_component/frontend/build/images/esg.svg
card_component/frontend/build/images/ev-car.svg
card_component/frontend/build/images/game.svg
card_component/frontend/build/images/growth.svg
card_component/frontend/build/images/kpop.svg
card_component/frontend/build/images/metaverse.svg
card_component/frontend/build/images/travel.svg
card_component/frontend/build/static/js/2.0d2a3d23.chunk.js
card_component/frontend/build/static/js/2.0d2a3d23.chunk.js.LICENSE.txt
card_component/frontend/build/static/js/2.0d2a3d23.chunk.js.map
card_component/frontend/build/static/js/main.cba81b6a.chunk.js
card_component/frontend/build/static/js/main.cba81b6a.chunk.js.map
card_component/frontend/build/static/js/runtime-main.657b0728.js
card_component/frontend/build/static/js/runtime-main.657b0728.js.map
card_component-0.0.2.dist-info/LICENSE
card_component-0.0.2.dist-info/METADATA
card_component-0.0.2.dist-info/WHEEL
card_component-0.0.2.dist-info/top_level.txt
card_component-0.0.2.dist-info/RECORD
